{
    "header" : "<%@ Page Language=\"VB\" %>",
    "social" : {
        "twitter" : "https://twitter.com/intent/tweet?original_referer=http%3A%2F%2Fjelastic.com%2F&source=tweetbutton&text=I've%20just%20deployed%20my%20first%20cloud%20app%20into%20Jelastic.%20Best%20.NET%20PaaS%20ever!&url=http%3A%2F%2Fjelastic.com%2F&via=jelastic",
        "facebook" : "http://www.facebook.com/sharer.php?u=https%3A%2F%2Fjelastic.com%2F&t=I've%20just%20deployed%20my%20first%20cloud%20app%20into%20Jelastic.%20Best%20.NET%20PaaS%20ever!",
        "google-plus" : "https://plus.google.com/share?url=http%3A%2F%2Fjelastic.com%2F&h1=en-US"
    },
    "usefulLinks" : {
        "left" : [
            {
                "text" : "Dashboard Guide",
                "href": "http://docs.jelastic.com/jelastic-dashboard-guide"
            },
            {
                "text" : "Upload your own .NET application",
                "href": "http://docs.jelastic.com/deploy-dotnet-archive-url"
            },
            {
                "text" : "Deploy .NET Projects via GIT or SVN",
                "href": "http://docs.jelastic.com/dotnet-git-svn"
            },
            {
                "text" : "Application Configuration",
                "href": "http://docs.jelastic.com/application-configuration"
            }
        ],
        "right" : [
            {
                "text" : "SSH Access",
                "href": "http://docs.jelastic.com/ssh-access"
            },
            {
                "text" : "FTP/FTPS Support",
                "href": "http://docs.jelastic.com/ftp-ftps-support"
            },
            {
                "text" : "Charged Resources",
                "href": "http://docs.jelastic.com/charged-resources"
            },
            {
                "text" : "Pricing Model",
                "href": "http://docs.jelastic.com/pricing-model"
            }
        ]
    },
    "year" : "\n<%= DateTime.Now.ToString(\"yyyy\") %>\n",
    "hostname" : "\n<%= System.Environment.MachineName %>\n"
}
